WinDeklar/EditableScene.py
WinDeklar/QTAux.py
WinDeklar/UploadProcedure.md
WinDeklar/WindowForm.py
WinDeklar/__init__.py
WinDeklar/drawing_example.yaml
WinDeklar/editable_items_metadata.yaml
WinDeklar/graph_aux.py
WinDeklar/input_panel_template.yaml
WinDeklar/points_box.py
WinDeklar/record.py
WinDeklar/signal_aux.py
WinDeklar/test_animation.py
WinDeklar/test_pyqt.py
WinDeklar/view_animation.py
WinDeklar/view_animation.yaml
WinDeklar/view_editable_drawing.py
WinDeklar/view_editable_drawing.yaml
WinDeklar/view_example.py
WinDeklar/view_example.yaml
WinDeklar/view_simple_graph.py
WinDeklar/yaml_functions.py
WinDeklar/icons/Arrows-ccw-01.svg
WinDeklar/icons/Move-07.svg
WinDeklar/icons/Move-horizontal-01.svg
WinDeklar/icons/move.png
WinDeklar/icons/notes_on_icons.txt
windeklar-0.4.3.dist-info/METADATA
windeklar-0.4.3.dist-info/WHEEL
windeklar-0.4.3.dist-info/licenses/LICENSE
windeklar-0.4.3.dist-info/RECORD
