Metadata-Version: 2.4
Name: WinDeklar
Version: 0.4.3
Summary: Create winforms in an easy, declarative way. Specially suited for Robotics applications
Project-URL: Homepage, https://github.com/njodal/WinDeklar
Project-URL: Bug Tracker, https://github.com/njodal/WinDeklar/issues
Author-email: Nicolas Jodal <jnj@genexus.com>
License-File: LICENSE
Classifier: License :: OSI Approved :: MIT License
Classifier: Operating System :: OS Independent
Classifier: Programming Language :: Python :: 3
Requires-Python: >=3.7
